nl2shell/__init__.py
nl2shell/main.py
mt_nl2shell-0.1.0.dist-info/METADATA
mt_nl2shell-0.1.0.dist-info/WHEEL
mt_nl2shell-0.1.0.dist-info/entry_points.txt
mt_nl2shell-0.1.0.dist-info/top_level.txt
mt_nl2shell-0.1.0.dist-info/RECORD
