Metadata-Version: 2.4
Name: mt-nl2shell
Version: 0.1.0
Summary: 将自然语言转换为shell命令的工具
Home-page: https://github.com/yourusername/nl2shell
Author: zhangwei330
Author-email: zhangwei330@meituan.com
Classifier: Programming Language :: Python :: 3
Classifier: License :: OSI Approved :: MIT License
Classifier: Operating System :: OS Independent
Requires-Python: >=3.6
Requires-Dist: openai
Requires-Dist: pyyaml
Requires-Dist: rich
Requires-Dist: psutil
Dynamic: author
Dynamic: author-email
Dynamic: classifier
Dynamic: description-content-type
Dynamic: home-page
Dynamic: requires-dist
Dynamic: requires-python
Dynamic: summary
